[
  {
    "zrpn": "125UIT1103",
    "name": "ISHWARI SHAMRAO ADE",
    "roll_no": "IT1101",
    "div": "A"
  },
  {
    "zrpn": "125UIT1095",
    "name": "ROHIT ASHOK BADAK",
    "roll_no": "IT1102",
    "div": "A"
  },
  {
    "zrpn": "125UIT1036",
    "name": "PRERANA SANDIP BANKAR",
    "roll_no": "IT1103",
    "div": "A"
  },
  {
    "zrpn": "125UIT1029",
    "name": "GAYATRI SANTOSH BARGAJE",
    "roll_no": "IT1104",
    "div": "A"
  },
  {
    "zrpn": "125UIT1090",
    "name": "SOHAM ABHAY BHAVSAR",
    "roll_no": "IT1105",
    "div": "A"
  },
  {
    "zrpn": "125UIT1148",
    "name": "AYUSH RAMBHAU BORKAR",
    "roll_no": "IT1106",
    "div": "A"
  },
  {
    "zrpn": "125UIT1061",
    "name": "CHAITANYA JYOTIRAM BHOSALE",
    "roll_no": "IT1107",
    "div": "A"
  },
  {
    "zrpn": "125UIT1137",
    "name": "PRANAV SHARAD CHOLE",
    "roll_no": "IT1108",
    "div": "A"
  },
  {
    "zrpn": "125UIT1074",
    "name": "PRUTHVIRAJ AMAR DALVE",
    "roll_no": "IT1109",
    "div": "A"
  },
  {
    "zrpn": "125UIT1147",
    "name": "SUMIT KISHOR DAVHALE",
    "roll_no": "IT1110",
    "div": "A"
  },
  {
    "zrpn": "125UIT1189",
    "name": "MADHUR SANJAY DHADVE",
    "roll_no": "IT1111",
    "div": "A"
  },
  {
    "zrpn": "125UIT1092",
    "name": "DIVY ANIL KOKATE",
    "roll_no": "IT1112",
    "div": "A"
  },
  {
    "zrpn": "125UIT1165",
    "name": "SHIVAMSINGH NARENDRASINGH DIXIT",
    "roll_no": "IT1113",
    "div": "A"
  },
  {
    "zrpn": "125UIT1122",
    "name": "PRANAV PRAVIN DOLASE",
    "roll_no": "IT1114",
    "div": "A"
  },
  {
    "zrpn": "125UIT1107",
    "name": "RISHI ASHOK GADAKH",
    "roll_no": "IT1115",
    "div": "A"
  },
  {
    "zrpn": "125UIT1065",
    "name": "SUJIT ARUN GARJE",
    "roll_no": "IT1116",
    "div": "A"
  },
  {
    "zrpn": "125UIT1125",
    "name": "GAURAV RAJENDRA NANVARE",
    "roll_no": "IT1117",
    "div": "A"
  },
  {
    "zrpn": "125UIT1212",
    "name": "SWARA SANTOSH GHARAT",
    "roll_no": "IT1118",
    "div": "A"
  },
  {
    "zrpn": "125UIT1019",
    "name": "ARJUN GAJANAN GHULE",
    "roll_no": "IT1119",
    "div": "A"
  },
  {
    "zrpn": "125UIT1130",
    "name": "SWARAJ VISHNU GODAMBE",
    "roll_no": "IT1120",
    "div": "A"
  },
  {
    "zrpn": "125UIT1033",
    "name": "YUVRAJSINHA RAVINDRA GOUR",
    "roll_no": "IT1121",
    "div": "A"
  },
  {
    "zrpn": "125UIT1116",
    "name": "PRUTHVIRAJ PRABHU INGLE",
    "roll_no": "IT1122",
    "div": "A"
  },
  {
    "zrpn": "125UIT1085",
    "name": "PRANAV PREMNATH KADAM",
    "roll_no": "IT1123",
    "div": "A"
  },
  {
    "zrpn": "125UIT1017",
    "name": "RASIKA SUHAS KALAMKAR",
    "roll_no": "IT1124",
    "div": "A"
  },
  {
    "zrpn": "125UIT1066",
    "name": "KISHOR MARATHE KANHAIYA",
    "roll_no": "IT1125",
    "div": "A"
  },
  {
    "zrpn": "125UIT1192",
    "name": "AYUSHI KIRAN KAWADE",
    "roll_no": "IT1126",
    "div": "A"
  },
  {
    "zrpn": "125UIT1204",
    "name": "SURAJ UDDHAV KHEDKAR",
    "roll_no": "IT1127",
    "div": "A"
  },
  {
    "zrpn": "125UIT1131",
    "name": "SAMRUDDHI SHAILESH KHODADE",
    "roll_no": "IT1128",
    "div": "A"
  },
  {
    "zrpn": "125UIT1016",
    "name": "RIDDHI KRUSHNA KHODE",
    "roll_no": "IT1129",
    "div": "A"
  },
  {
    "zrpn": "125UIT1001",
    "name": "SHUBHAM PRAVIN LAHAMGE",
    "roll_no": "IT1130",
    "div": "A"
  },
  {
    "zrpn": "125UIT1211",
    "name": "ARNAV RAJAN MACHAREKAR",
    "roll_no": "IT1131",
    "div": "A"
  },
  {
    "zrpn": "125UIT1035",
    "name": "ADITYA SUNIL MAHURE",
    "roll_no": "IT1132",
    "div": "A"
  },
  {
    "zrpn": "125UIT1197",
    "name": "BUSHARA MEHMUD MOMIN",
    "roll_no": "IT1133",
    "div": "A"
  },
  {
    "zrpn": "125UIT1038",
    "name": "MAHESHWARI SANDIP OROKAR",
    "roll_no": "IT1134",
    "div": "A"
  },
  {
    "zrpn": "125UIT1048",
    "name": "SURAJ NARESH PADWAL",
    "roll_no": "IT1135",
    "div": "A"
  },
  {
    "zrpn": "125UIT1111",
    "name": "ROHAN RAMESH PANCHAL",
    "roll_no": "IT1136",
    "div": "A"
  },
  {
    "zrpn": "125UIT1040",
    "name": "ROHINI GAUDAPPA PATIL",
    "roll_no": "IT1137",
    "div": "A"
  },
  {
    "zrpn": "125UIT1076",
    "name": "KARAN BABURAO PAWAR",
    "roll_no": "IT1138",
    "div": "A"
  },
  {
    "zrpn": "125UIT1067",
    "name": "SATYAM HIRAMAN PAWAR",
    "roll_no": "IT1139",
    "div": "A"
  },
  {
    "zrpn": "125UIT1118",
    "name": "SHUBHANGI VIJAY PAYGUDE",
    "roll_no": "IT1140",
    "div": "A"
  },
  {
    "zrpn": "125UIT1139",
    "name": "TUSHAR VIVEK POTDAR",
    "roll_no": "IT1141",
    "div": "A"
  },
  {
    "zrpn": "125UIT1075",
    "name": "RUCHIRA RAVI POTRAJE",
    "roll_no": "IT1142",
    "div": "A"
  },
  {
    "zrpn": "125UIT1187",
    "name": "VIVEK KULKARNI PRASAD",
    "roll_no": "IT1143",
    "div": "A"
  },
  {
    "zrpn": "125UIT1155",
    "name": "PAVAN AMAR RAMGUDE",
    "roll_no": "IT1144",
    "div": "A"
  },
  {
    "zrpn": "125UIT1108",
    "name": "DISHA AVINASH RATHOD",
    "roll_no": "IT1145",
    "div": "A"
  },
  {
    "zrpn": "125UIT1043",
    "name": "RAJ NEPAL RATHOD",
    "roll_no": "IT1146",
    "div": "A"
  },
  {
    "zrpn": "125UIT1182",
    "name": "RUTUJA SANJIVKUMAR PANCHAL",
    "roll_no": "IT1147",
    "div": "A"
  },
  {
    "zrpn": "125UIT1199",
    "name": "SADICHHA KALIDAS PAWAR",
    "roll_no": "IT1148",
    "div": "A"
  },
  {
    "zrpn": "125UIT1132",
    "name": "ADITYA PANDHARINATH SATPUTE",
    "roll_no": "IT1149",
    "div": "A"
  },
  {
    "zrpn": "125UIT1080",
    "name": "AJAY VINOD SHEVARE",
    "roll_no": "IT1150",
    "div": "A"
  },
  {
    "zrpn": "125UIT1171",
    "name": "TEJASWINI PRAKASH SHINDE",
    "roll_no": "IT1151",
    "div": "A"
  },
  {
    "zrpn": "125UIT1180",
    "name": "SHRAWANI KRISHNA ROKDE",
    "roll_no": "IT1152",
    "div": "A"
  },
  {
    "zrpn": "125UIT1004",
    "name": "SHRINIDHI MADHAV SHINDE",
    "roll_no": "IT1153",
    "div": "A"
  },
  {
    "zrpn": "125UIT1120",
    "name": "SHUBHAM MACHHINDRA SURVASE",
    "roll_no": "IT1154",
    "div": "A"
  },
  {
    "zrpn": "125UIT1209",
    "name": "SIDDHESH VINODKUMAR DHAVALE",
    "roll_no": "IT1155",
    "div": "A"
  },
  {
    "zrpn": "125UIT1110",
    "name": "NAVYA RAJKUMAR SINGH",
    "roll_no": "IT1156",
    "div": "A"
  },
  {
    "zrpn": "125UIT1024",
    "name": "SOHAM SIDDHESHWAR SOLANKAR",
    "roll_no": "IT1157",
    "div": "A"
  },
  {
    "zrpn": "125UIT1140",
    "name": "SUCHITA RAMCHANDRA SIHORE",
    "roll_no": "IT1159",
    "div": "A"
  },
  {
    "zrpn": "125UIT1086",
    "name": "VALLABH KSHITIJ SURVE",
    "roll_no": "IT1160",
    "div": "A"
  },
  {
    "zrpn": "125UIT1145",
    "name": "SWARANJALI OMPRAKASH GHODKE",
    "roll_no": "IT1161",
    "div": "A"
  },
  {
    "zrpn": "125UIT1206",
    "name": "SWAROOP SATISH PARDESHI",
    "roll_no": "IT1162",
    "div": "A"
  },
  {
    "zrpn": "125UIT1002",
    "name": "PARTH NITIN TANTAK",
    "roll_no": "IT1163",
    "div": "A"
  },
  {
    "zrpn": "125UIT1022",
    "name": "MAYURI MAROTI UGLE",
    "roll_no": "IT1164",
    "div": "A"
  },
  {
    "zrpn": "125UIT1195",
    "name": "SOHAM SHASHIKANT UNDALE",
    "roll_no": "IT1165",
    "div": "A"
  },
  {
    "zrpn": "125UIT1156",
    "name": "VAISHNAVI AVINASH KANDHARE",
    "roll_no": "IT1166",
    "div": "A"
  },
  {
    "zrpn": "125UIT1149",
    "name": "SRUSHTI SANTOSH WAGHMALE",
    "roll_no": "IT1167",
    "div": "A"
  },
  {
    "zrpn": "125UIT1101",
    "name": "ASHWINI SAMBHAJI ANPAT",
    "roll_no": "IT1201",
    "div": "B"
  },
  {
    "zrpn": "125UIT1104",
    "name": "ARYAN RAMESH PATIL",
    "roll_no": "IT1202",
    "div": "B"
  },
  {
    "zrpn": "125UIT1082",
    "name": "SOHAM SACHIN BAHIRAT",
    "roll_no": "IT1203",
    "div": "B"
  },
  {
    "zrpn": "125UIT1012",
    "name": "PRATIK HANMANT BHADRE",
    "roll_no": "IT1204",
    "div": "B"
  },
  {
    "zrpn": "125UIT1039",
    "name": "SHRADHA SHIVANAND BIRADAR",
    "roll_no": "IT1205",
    "div": "B"
  },
  {
    "zrpn": "125UIT1089",
    "name": "MAYURA SANTOSH BOBADE",
    "roll_no": "IT1206",
    "div": "B"
  },
  {
    "zrpn": "125UIT1053",
    "name": "ROHAN GAJANAN DAMARE",
    "roll_no": "IT1207",
    "div": "B"
  },
  {
    "zrpn": "125UIT1006",
    "name": "YASH MANOJ DUBEY",
    "roll_no": "IT1208",
    "div": "B"
  },
  {
    "zrpn": "125UIT1023",
    "name": "SHRUTI SANTOSHRAO FUND",
    "roll_no": "IT1209",
    "div": "B"
  },
  {
    "zrpn": "125UIT1060",
    "name": "ANUSHKA BHUSHAN GARSE",
    "roll_no": "IT1210",
    "div": "B"
  },
  {
    "zrpn": "125UIT1205",
    "name": "SHRIPRASAD DHANANJAY GHONE",
    "roll_no": "IT1211",
    "div": "B"
  },
  {
    "zrpn": "125UIT1073",
    "name": "DHRUV AMAR GODSE",
    "roll_no": "IT1212",
    "div": "B"
  },
  {
    "zrpn": "125UIT1154",
    "name": "KISHOR BHALEKAR GRISHMA",
    "roll_no": "IT1213",
    "div": "B"
  },
  {
    "zrpn": "125UIT1128",
    "name": "PRANAY DATTA HAPSE",
    "roll_no": "IT1214",
    "div": "B"
  },
  {
    "zrpn": "125UIT1037",
    "name": "HARSHITA JIGNESH MEHTA",
    "roll_no": "IT1215",
    "div": "B"
  },
  {
    "zrpn": "125UIT1142",
    "name": "YASH VINODBHAI JADHAV",
    "roll_no": "IT1216",
    "div": "B"
  },
  {
    "zrpn": "125UIT1124",
    "name": "BHAVANA BALRAM JAKKA",
    "roll_no": "IT1217",
    "div": "B"
  },
  {
    "zrpn": "125UIT1030",
    "name": "CHANVIR SHIVPUTRA JAMADAR",
    "roll_no": "IT1218",
    "div": "B"
  },
  {
    "zrpn": "125UIT1159",
    "name": "SHLOK MILIND KAKADE",
    "roll_no": "IT1219",
    "div": "B"
  },
  {
    "zrpn": "125UIT1179",
    "name": "SUMIT SUBHASH KALE",
    "roll_no": "IT1220",
    "div": "B"
  },
  {
    "zrpn": "125UIT1100",
    "name": "SHAILAJA SURESH KAMBLE",
    "roll_no": "IT1221",
    "div": "B"
  },
  {
    "zrpn": "125UIT1163",
    "name": "SHUBHAM BASWANT KANDURKE",
    "roll_no": "IT1222",
    "div": "B"
  },
  {
    "zrpn": "125UIT1183",
    "name": "SHYAMSUNDAR RAMDAS KANTHALE",
    "roll_no": "IT1223",
    "div": "B"
  },
  {
    "zrpn": "125UIT1176",
    "name": "ANKITA RAMESHWAR KHURUSANE",
    "roll_no": "IT1224",
    "div": "B"
  },
  {
    "zrpn": "125UIT1083",
    "name": "JAY SAHEBRAO KOHINKAR",
    "roll_no": "IT1225",
    "div": "B"
  },
  {
    "zrpn": "125UIT1146",
    "name": "KULASHREE HITENDRA KULKARNI",
    "roll_no": "IT1226",
    "div": "B"
  },
  {
    "zrpn": "125UIT1056",
    "name": "MEGHRAJ DEEPAK MASKE",
    "roll_no": "IT1227",
    "div": "B"
  },
  {
    "zrpn": "125UIT1008",
    "name": "KHUSHHALI PRAMOD MISHRA",
    "roll_no": "IT1228",
    "div": "B"
  },
  {
    "zrpn": "125UIT1021",
    "name": "PRITI DAYANAND MULE",
    "roll_no": "IT1229",
    "div": "B"
  },
  {
    "zrpn": "125UIT1203",
    "name": "PAPPU KANOUJIYA NIKHIL",
    "roll_no": "IT1230",
    "div": "B"
  },
  {
    "zrpn": "125UIT1028",
    "name": "GAYATRI PRASHANT PATIL",
    "roll_no": "IT1231",
    "div": "B"
  },
  {
    "zrpn": "125UIT1009",
    "name": "VIGHNESH KAILAS PATIL",
    "roll_no": "IT1232",
    "div": "B"
  },
  {
    "zrpn": "125UIT1068",
    "name": "YASHWANT TANAJI PATIL",
    "roll_no": "IT1233",
    "div": "B"
  },
  {
    "zrpn": "125UIT1123",
    "name": "UTKARSH YOGESH PAWAR",
    "roll_no": "IT1234",
    "div": "B"
  },
  {
    "zrpn": "125UIT1051",
    "name": "ROSHAN HATZADE PRANIT",
    "roll_no": "IT1235",
    "div": "B"
  },
  {
    "zrpn": "125UIT1109",
    "name": "SUHAS KASHID PRATHAMESH",
    "roll_no": "IT1236",
    "div": "B"
  },
  {
    "zrpn": "125UIT1138",
    "name": "GAURAV GANESH SALAVE",
    "roll_no": "IT1237",
    "div": "B"
  },
  {
    "zrpn": "125UIT1052",
    "name": "RAKHI SURESH SALUNKE",
    "roll_no": "IT1238",
    "div": "B"
  },
  {
    "zrpn": "125UIT1119",
    "name": "RAHUL SATHE SAMIKSHA",
    "roll_no": "IT1239",
    "div": "B"
  },
  {
    "zrpn": "125UIT1013",
    "name": "SWAYAM PRAKASH SAMRATKAR",
    "roll_no": "IT1240",
    "div": "B"
  },
  {
    "zrpn": "125UIT1135",
    "name": "GAURAV VIJAYANAND SANGORE",
    "roll_no": "IT1241",
    "div": "B"
  },
  {
    "zrpn": "125UIT1042",
    "name": "SAKSHI SUNIL SAWALE",
    "roll_no": "IT1242",
    "div": "B"
  },
  {
    "zrpn": "125UIT1136",
    "name": "MEGHRAJ KISHOR SHAHANE",
    "roll_no": "IT1243",
    "div": "B"
  },
  {
    "zrpn": "125UIT1105",
    "name": "GAURI SANTOSH SHENDAGE",
    "roll_no": "IT1244",
    "div": "B"
  },
  {
    "zrpn": "125UIT1127",
    "name": "VAISHNAVI SHAHAJI SHIVADE",
    "roll_no": "IT1245",
    "div": "B"
  },
  {
    "zrpn": "125UIT1034",
    "name": "SANDIP WAVDHANE SHRUTI",
    "roll_no": "IT1246",
    "div": "B"
  },
  {
    "zrpn": "125UIT1208",
    "name": "IRAM UZAIR AHMAD SIDDIQUI",
    "roll_no": "IT1247",
    "div": "B"
  },
  {
    "zrpn": "125UIT1106",
    "name": "MAYUR MADHAV SOMWARE",
    "roll_no": "IT1248",
    "div": "B"
  },
  {
    "zrpn": "125UIT1186",
    "name": "MANASI SANDIP SONAWANE",
    "roll_no": "IT1249",
    "div": "B"
  },
  {
    "zrpn": "125UIT1077",
    "name": "MANSI ROHIDAS SONAWANE",
    "roll_no": "IT1250",
    "div": "B"
  },
  {
    "zrpn": "125UIT1062",
    "name": "ATHARV SANJAY SONI",
    "roll_no": "IT1251",
    "div": "B"
  },
  {
    "zrpn": "125UIT1078",
    "name": "SURESH KHAIRE SUDIKSHA",
    "roll_no": "IT1252",
    "div": "B"
  },
  {
    "zrpn": "125UIT1049",
    "name": "DIPESH SAWANT SUSMIT",
    "roll_no": "IT1253",
    "div": "B"
  },
  {
    "zrpn": "125UIT1014",
    "name": "SAMARTHA VISHAL SUTAR",
    "roll_no": "IT1254",
    "div": "B"
  },
  {
    "zrpn": "125UIT1046",
    "name": "SNEHA VIVEK SWAMI",
    "roll_no": "IT1255",
    "div": "B"
  },
  {
    "zrpn": "125UIT1005",
    "name": "IQRA IRFAN TAMBOLI",
    "roll_no": "IT1256",
    "div": "B"
  },
  {
    "zrpn": "125UIT1091",
    "name": "BASVARAJ UMAKANT TAMMEWAR",
    "roll_no": "IT1257",
    "div": "B"
  },
  {
    "zrpn": "125UIT1010",
    "name": "UDAY SUNIL TEMBHURNE",
    "roll_no": "IT1258",
    "div": "B"
  },
  {
    "zrpn": "125UIT1058",
    "name": "AADESH RAMESHWAR THANGE",
    "roll_no": "IT1259",
    "div": "B"
  },
  {
    "zrpn": "125UIT1210",
    "name": "VARUN TAPISE VASUNDHARA",
    "roll_no": "IT1260",
    "div": "B"
  },
  {
    "zrpn": "125UIT1045",
    "name": "ATHARV NAGESH VYAVAHARE",
    "roll_no": "IT1261",
    "div": "B"
  },
  {
    "zrpn": "125UIT1168",
    "name": "SHUBHAM CHANDRAKANT WANKHEDE",
    "roll_no": "IT1262",
    "div": "B"
  },
  {
    "zrpn": "125UIT1152",
    "name": "SHREYA SUDAM WAPHARE",
    "roll_no": "IT1263",
    "div": "B"
  },
  {
    "zrpn": "125UIT1126",
    "name": "JANHAVI HEMANT WAVHAL",
    "roll_no": "IT1264",
    "div": "B"
  },
  {
    "zrpn": "125UIT1200",
    "name": "SAKSHI RAHUL ZENDE",
    "roll_no": "IT1265",
    "div": "B"
  },
  {
    "zrpn": "125UIT1003",
    "name": "AARYAN BIPIN SHAHA",
    "roll_no": "",
    "div": "A"
  },
  {
    "zrpn": "125UIT1173",
    "name": "ANKITA SHAILENDRA MAGAR",
    "roll_no": "",
    "div": "A"
  },
  {
    "zrpn": "125UIT1081",
    "name": "AMOL MACHHINDRA BAHIR",
    "roll_no": "",
    "div": "A"
  },
  {
    "zrpn": "125UIT1191",
    "name": "SANSKRUTI BHUSHAN BAIT",
    "roll_no": "",
    "div": "A"
  },
  {
    "zrpn": "125UIT1027",
    "name": "ATHARVA MANOJ BHARDWAJ",
    "roll_no": "",
    "div": "A"
  },
  {
    "zrpn": "125UIT1097",
    "name": "ADITYA VENUDAS BHENDEKAR",
    "roll_no": "",
    "div": "A"
  },
  {
    "zrpn": "125UIT1007",
    "name": "Vaibhav Mahadev Bodke",
    "roll_no": "",
    "div": "A"
  },
  {
    "zrpn": "125UIT1047",
    "name": "BORAWAKE YASHRAJ PRASHANT",
    "roll_no": "",
    "div": "A"
  },
  {
    "zrpn": "125UIT1213",
    "name": "VAISHNAV DINKAR BURKUL",
    "roll_no": "",
    "div": "A"
  },
  {
    "zrpn": "125UIT1059",
    "name": "CHAKOTE TANVI GAJANAN",
    "roll_no": "",
    "div": "A"
  },
  {
    "zrpn": "125UIT1166",
    "name": "SHRIHARI ARUN CHINCHAKAR",
    "roll_no": "",
    "div": "A"
  },
  {
    "zrpn": "125UIT1050",
    "name": "DAVRE SAMEEP KANISHK",
    "roll_no": "",
    "div": "A"
  },
  {
    "zrpn": "125UIT1099",
    "name": "ABHISHEK VIJAY DESHMUKH",
    "roll_no": "",
    "div": "A"
  },
  {
    "zrpn": "125UIT1143",
    "name": "SHALAKA MADHAORAO DESHMUKH",
    "roll_no": "",
    "div": "A"
  },
  {
    "zrpn": "125UIT1098",
    "name": "OMKAR NITIN DHAMAL",
    "roll_no": "",
    "div": "A"
  },
  {
    "zrpn": "125UIT1193",
    "name": "VARSHA NANASAHEB DHERE",
    "roll_no": "",
    "div": "A"
  },
  {
    "zrpn": "125UIT1041",
    "name": "ABHAY RAMESHWAR GADADE",
    "roll_no": "",
    "div": "A"
  },
  {
    "zrpn": "125UIT1133",
    "name": "SWAPNEEL RAJENDRA GANJURE",
    "roll_no": "",
    "div": "A"
  },
  {
    "zrpn": "125UIT1096",
    "name": "GITE SHUBHAM RAJENDRA",
    "roll_no": "",
    "div": "A"
  },
  {
    "zrpn": "125UIT1178",
    "name": "POONAM RAVSAHEB GITTE",
    "roll_no": "",
    "div": "A"
  },
  {
    "zrpn": "125UIT1113",
    "name": "HARIOM NANA KATWATE",
    "roll_no": "",
    "div": "A"
  },
  {
    "zrpn": "125UIT1157",
    "name": "PRARTHANA UTTAMRAO INGLE",
    "roll_no": "",
    "div": "A"
  },
  {
    "zrpn": "125UIT1121",
    "name": "RUTUJA VILASRAO KAHADE",
    "roll_no": "",
    "div": "A"
  },
  {
    "zrpn": "125UIT1044",
    "name": "ADITIYA VINOD KALASKAR",
    "roll_no": "",
    "div": "A"
  },
  {
    "zrpn": "125UIT1011",
    "name": "Ajit Vishnu Karad",
    "roll_no": "",
    "div": "A"
  },
  {
    "zrpn": "125UIT1084",
    "name": "DNYANESHWAR VITTHAL KHATING",
    "roll_no": "",
    "div": "A"
  },
  {
    "zrpn": "125UIT1088",
    "name": "KISHOR GANESHRAO PANCHAL",
    "roll_no": "",
    "div": "A"
  },
  {
    "zrpn": "125UIT1114",
    "name": "SHRAVANI PRAMOD KULKARNI",
    "roll_no": "",
    "div": "A"
  },
  {
    "zrpn": "125UIT1175",
    "name": "Kunte Ankita Bharat",
    "roll_no": "",
    "div": "A"
  },
  {
    "zrpn": "125UIT1214",
    "name": "LAXMIKANT JAWAHAR GUPTA",
    "roll_no": "",
    "div": "A"
  },
  {
    "zrpn": "125UIT1115",
    "name": "MAHESH RAVINDRA PADSE",
    "roll_no": "",
    "div": "A"
  },
  {
    "zrpn": "125UIT1185",
    "name": "MOHAMMED KAIF IRSHAD KHAN",
    "roll_no": "",
    "div": "A"
  },
  {
    "zrpn": "125UIT1102",
    "name": "SRUSHTI HANUMANT MOKASHE",
    "roll_no": "",
    "div": "A"
  },
  {
    "zrpn": "125UIT1025",
    "name": "RAVINDRA CHANDRAKANT MUDE",
    "roll_no": "",
    "div": "A"
  },
  {
    "zrpn": "125UIT1112",
    "name": "NAKUL SANJAY WAGHMARE",
    "roll_no": "",
    "div": "A"
  },
  {
    "zrpn": "125UIT1194",
    "name": "YASHRAJ VINAYAK NANAWARE",
    "roll_no": "",
    "div": "A"
  },
  {
    "zrpn": "125UIT1063",
    "name": "ISHWARI VINOD NIKAM",
    "roll_no": "",
    "div": "A"
  },
  {
    "zrpn": "125UIT1054",
    "name": "NIRWAL AISHWARYA GOPALRAO",
    "roll_no": "",
    "div": "A"
  },
  {
    "zrpn": "125UIT1020",
    "name": "ASHWIN GURUPRASAD PANDE",
    "roll_no": "",
    "div": "A"
  },
  {
    "zrpn": "125UIT1202",
    "name": "BHAGYASHREE GOPAL PATIL",
    "roll_no": "",
    "div": "A"
  },
  {
    "zrpn": "125UIT1031",
    "name": "GITAL KETAN PATIL",
    "roll_no": "",
    "div": "A"
  },
  {
    "zrpn": "125UIT1069",
    "name": "PATIL MOHIT SUNIL",
    "roll_no": "",
    "div": "A"
  },
  {
    "zrpn": "125UIT1117",
    "name": "POKALE SHRIRAM PANDURANG",
    "roll_no": "",
    "div": "A"
  },
  {
    "zrpn": "125UIT1151",
    "name": "POORVA RAMESH BANKAR",
    "roll_no": "",
    "div": "A"
  },
  {
    "zrpn": "125UIT1190",
    "name": "PRAVIN SHIVAJI KADU",
    "roll_no": "",
    "div": "A"
  },
  {
    "zrpn": "125UIT1070",
    "name": "RANA HIRWANE VARDHAN RAKESH",
    "roll_no": "",
    "div": "A"
  },
  {
    "zrpn": "125UIT1093",
    "name": "NIKHIL SANTOSH RAUT",
    "roll_no": "",
    "div": "A"
  },
  {
    "zrpn": "125UIT1055",
    "name": "RUSHIKESH AMOL RAUT",
    "roll_no": "",
    "div": "A"
  },
  {
    "zrpn": "125UIT1018",
    "name": "YASH SANTOSH SALGAR",
    "roll_no": "",
    "div": "A"
  },
  {
    "zrpn": "125UIT1141",
    "name": "SAMARTH PAWAN JAJU",
    "roll_no": "",
    "div": "A"
  },
  {
    "zrpn": "125UIT1172",
    "name": "SHAIKH AHAD SHAIKH SAMAD",
    "roll_no": "",
    "div": "A"
  },
  {
    "zrpn": "125UIT1032",
    "name": "SHREYASH UMESH SHEDGE",
    "roll_no": "",
    "div": "A"
  },
  {
    "zrpn": "125UIT1201",
    "name": "SHRAVANI SACHIN BUGAD",
    "roll_no": "",
    "div": "A"
  },
  {
    "zrpn": "125UIT1057",
    "name": "YASH MACHHINDRA SUDRIK",
    "roll_no": "",
    "div": "A"
  },
  {
    "zrpn": "125UIT1079",
    "name": "SUMEDH MAHADEV KHALIKAR",
    "roll_no": "",
    "div": "A"
  },
  {
    "zrpn": "125UIT1161",
    "name": "VAISHNAVI BHARAT TALEKAR",
    "roll_no": "",
    "div": "A"
  },
  {
    "zrpn": "125UIT1015",
    "name": "ANUSHKA GANESH THOMBARE",
    "roll_no": "",
    "div": "A"
  },
  {
    "zrpn": "125UIT1170",
    "name": "Pavan Vitthal Thote",
    "roll_no": "",
    "div": "A"
  },
  {
    "zrpn": "125UIT1129",
    "name": "PRAJAKTA LAXMAN TIRUKE",
    "roll_no": "",
    "div": "A"
  },
  {
    "zrpn": "125UIT1072",
    "name": "UBALE PIYUSH KAILASH",
    "roll_no": "",
    "div": "A"
  },
  {
    "zrpn": "125UIT1162",
    "name": "UMALE SUBODH SHANTARAM",
    "roll_no": "",
    "div": "A"
  },
  {
    "zrpn": "125UIT1087",
    "name": "TARWADE VAIBHAV WAMAN",
    "roll_no": "",
    "div": "A"
  },
  {
    "zrpn": "125UIT1071",
    "name": "SAYALI DNYANOBA VAIDYA",
    "roll_no": "",
    "div": "A"
  },
  {
    "zrpn": "125UIT1167",
    "name": "VAISHNAVI PRAMOD SUTAR",
    "roll_no": "",
    "div": "A"
  }
]